<?xml version="1.0" encoding="UTF-8"?>
<!DOCTYPE suite SYSTEM "https://testng.org/testng-1.0.dtd">
<suite name="Suite" parallel="tests" thread-count="3">
  <test name="chrometest">
   <parameter name="browser" value="chrome"></parameter>
  
    <classes>
    
      <class name="com.testcases.LOGINPAGEtest"/>
      
    </classes>
  </test> <!-- Test -->
  
  
   <test  name="firefoxtest">
   <parameter name="browser" value="firefox"></parameter>
  
    <classes>
    
      <class name="com.testcases.LOGINPAGEtest"/>
      
    </classes>
  </test> <!-- Test -->
   <test  name="IEtest">
   <parameter name="browser" value="IE"></parameter>
  
    <classes>
    
      <class name="com.testcases.LOGINPAGEtest"/>
      
    </classes>
  </test> <!-- Test -->
</suite> <!-- Suite -->
